{
  "generator-jhipster": {
    "promptValues": {
      "packageName": "com.wefine.app",
      "nativeLanguage": "zh-cn"
    },
    "jhipsterVersion": "4.3.0",
    "baseName": "tms",
    "packageName": "com.wefine.app",
    "packageFolder": "com/wefine/app",
    "serverPort": "8080",
    "authenticationType": "session",
    "hibernateCache": "ehcache",
    "clusteredHttpSession": false,
    "websocket": false,
    "databaseType": "sql",
    "devDatabaseType": "mysql",
    "prodDatabaseType": "mysql",
    "searchEngine": false,
    "messageBroker": false,
    "serviceDiscoveryType": false,
    "buildTool": "maven",
    "enableSocialSignIn": false,
    "rememberMeKey": "f13d99a15448eaac0eec3bcf623af88eddeb10a4",
    "clientFramework": "angular2",
    "useSass": false,
    "clientPackageManager": "yarn",
    "applicationType": "monolith",
    "testFrameworks": [
      "protractor"
    ],
    "jhiPrefix": "jhi",
    "enableTranslation": true,
    "nativeLanguage": "zh-cn",
    "languages": [
      "zh-cn",
      "en"
    ]
  }
}